pymathutils/__init__.py
pymathutils/findiff.py
pymathutils/jit_funs.py
pymathutils/mathutils_backend.cpython-313-x86_64-linux-gnu.so
pymathutils/special.py
pymathutils-0.1.24.dist-info/METADATA
pymathutils-0.1.24.dist-info/WHEEL
pymathutils-0.1.24.dist-info/RECORD
